CHANGES.txt
MANIFEST.in
README.txt
setup.cfg
setup.py
Products/__init__.py
Products/__init__.pyc
Products.OrderableReferenceField.egg-info/PKG-INFO
Products.OrderableReferenceField.egg-info/SOURCES.txt
Products.OrderableReferenceField.egg-info/dependency_links.txt
Products.OrderableReferenceField.egg-info/entry_points.txt
Products.OrderableReferenceField.egg-info/namespace_packages.txt
Products.OrderableReferenceField.egg-info/not-zip-safe
Products.OrderableReferenceField.egg-info/requires.txt
Products.OrderableReferenceField.egg-info/top_level.txt
Products/OrderableReferenceField/__init__.py
Products/OrderableReferenceField/_field.py
Products/OrderableReferenceField/config.py
Products/OrderableReferenceField/configure.zcml
Products/OrderableReferenceField/examples/__init__.py
Products/OrderableReferenceField/examples/contact.py
Products/OrderableReferenceField/examples/favorite.py
Products/OrderableReferenceField/profiles/default/cssregistry.xml
Products/OrderableReferenceField/profiles/default/jsregistry.xml
Products/OrderableReferenceField/profiles/default/metadata.xml
Products/OrderableReferenceField/profiles/default/skins.xml
Products/OrderableReferenceField/profiles/example/metadata.xml
Products/OrderableReferenceField/profiles/example/types.xml
Products/OrderableReferenceField/profiles/example/types/ContactPerson.xml
Products/OrderableReferenceField/profiles/example/types/MyFavorite.xml
Products/OrderableReferenceField/profiles/uninstall/cssregistry.xml
Products/OrderableReferenceField/profiles/uninstall/jsregistry.xml
Products/OrderableReferenceField/profiles/uninstall/metadata.xml
Products/OrderableReferenceField/profiles/uninstall/skins.xml
Products/OrderableReferenceField/skins/orderablereferencefield/orderablereference.css.dtml
Products/OrderableReferenceField/skins/orderablereferencefield/orderablereference.js
Products/OrderableReferenceField/skins/orderablereferencefield/orderablereference.pt
Products/OrderableReferenceField/tests/__init__.py
Products/OrderableReferenceField/tests/base.py
Products/OrderableReferenceField/tests/test_field.py
Products/OrderableReferenceField/tests/test_setup.py
Products/OrderableReferenceField/tests/test_skins.py
docs/INSTALL.txt
docs/LICENSE.GPL
docs/LICENSE.txt