Metadata-Version: 1.0
Name: Products.OrderableReferenceField
Version: 1.2-beta3
Summary: This product provides an Archetype field that's very similiar         to the Archetypes Reference field, with the addition that it stores the         order of referenced objects
Home-page: http://svn.plone.org/svn/archetypes/Products.OrderableReferenceField/
Author: Daniel Nouri
Author-email: daniel.nouri@gmail.com
License: GPL
Platform: UNKNOWN
Classifier: Framework :: Plone
Classifier: Programming Language :: Python
Classifier: Topic :: Software Development :: Libraries :: Python Modules
